metronetpy/__init__.py
metronetpy/__version__.py
metronetpy/bridge.py
metronetpy/iess.py
metronetpy-0.3.0.data/scripts/metronet
metronetpy-0.3.0.dist-info/AUTHORS.md
metronetpy-0.3.0.dist-info/LICENSE
metronetpy-0.3.0.dist-info/METADATA
metronetpy-0.3.0.dist-info/WHEEL
metronetpy-0.3.0.dist-info/top_level.txt
metronetpy-0.3.0.dist-info/RECORD
