Metadata-Version: 2.1
Name: metronetpy
Version: 0.3.0
Summary: Python Package for programmatically controlling Security and Intrusion systems made by IESS
Home-page: https://github.com/tulindo/metronetpy
Author: Paolo Tuninetto
Author-email: paolo.tuninetto@gmail.com
License: UNKNOWN
Platform: UNKNOWN
Classifier: Programming Language :: Python :: 3
Classifier: License :: OSI Approved :: GNU General Public License v3 (GPLv3)
Classifier: Operating System :: OS Independent
Classifier: Development Status :: 3 - Alpha
Requires-Python: >=3.7
Requires-Dist: requests
Requires-Dist: pyyaml
Requires-Dist: sslkeylog
